MapCoords/__init__.py
MapCoords/coord_transform.py
MapCoords/dis_compute.py
MapCoords/rings.py
MapCoords/city_rings/__init__.py
MapCoords/crawl_city_ring_coords/__init__.py
MapCoords/data_demo/__init__.py
MapCoords/html_templates/__init__.py
MapCoords-0.1.8.dist-info/LICENSE
MapCoords-0.1.8.dist-info/METADATA
MapCoords-0.1.8.dist-info/WHEEL
MapCoords-0.1.8.dist-info/top_level.txt
MapCoords-0.1.8.dist-info/RECORD
