Metadata-Version: 2.1
Name: MapCoords
Version: 0.1.8
Summary: A Python library about map coordinates
Home-page: https://github.com/Ijustwantyouhappy/MapCoords
Author: Ijustwantyouhappy
Author-email: 
License: MIT
Project-URL: GitHub, https://github.com/Ijustwantyouhappy/MapCoords
Project-URL: Source, https://github.com/Ijustwantyouhappy/MapCoords
Keywords: map coordinates
Platform: UNKNOWN
Classifier: Environment :: Web Environment
Classifier: Intended Audience :: Developers
Classifier: License :: OSI Approved :: MIT License
Classifier: Topic :: Software Development :: Libraries :: Python Modules
Classifier: Programming Language :: Python :: 3
Requires-Python: >=3.5
Requires-Dist: numpy (>=1.14.2)
Requires-Dist: scipy (>=1.1.0)
Requires-Dist: pandas (>=0.22.0)
Requires-Dist: matplotlib (>=2.0.2)
Requires-Dist: h5py (>=2.8.0)
Requires-Dist: requests (>=2.14.2)
